incognita/logger.py
incognita/data/add_shape_data.py
incognita/data/ons_pd.py
incognita/data/scout_census.py
incognita/geographies/district_boundaries.py
incognita/geographies/geography.py
incognita/maps/map.py
incognita/preprocessing/census_merge_data.py
incognita/preprocessing/setup_data_file.py
incognita/preprocessing/setup_reduce_onspd.py
incognita/reports/history_summary.py
incognita/reports/reports.py
incognita/utility/config.py
incognita/utility/constants.py
incognita/utility/deciles.py
incognita/utility/filter.py
incognita/utility/report_io.py
incognita/utility/root.py
incognita/utility/timing.py
incognita-0.28.0.dist-info/LICENSE
incognita-0.28.0.dist-info/METADATA
incognita-0.28.0.dist-info/WHEEL
incognita-0.28.0.dist-info/top_level.txt
incognita-0.28.0.dist-info/RECORD
