Metadata-Version: 2.1
Name: incognita
Version: 0.28.0
Summary: Mapping the annual UK Scout Census to local geographies
Home-page: https://github.com/the-scouts/incognita
Author: Adam Turner, Tom Yems
License: MIT
Keywords: API, scouts
Platform: any
Classifier: Development Status :: 3 - Alpha
Classifier: Intended Audience :: Developers
Classifier: License :: OSI Approved :: MIT License
Classifier: Operating System :: OS Independent
Classifier: Programming Language :: Python :: 3 :: Only
Classifier: Programming Language :: Python :: 3.9
Classifier: Programming Language :: Python :: Implementation :: CPython
Classifier: Programming Language :: Python :: Implementation :: PyPy
Classifier: Topic :: Software Development
Classifier: Topic :: Utilities
Requires-Python: >=3.9
License-File: LICENSE
Requires-Dist: pandas
Requires-Dist: numpy
Requires-Dist: geopandas (>=0.8)
Requires-Dist: shapely
Requires-Dist: pyarrow
Requires-Dist: pygeos
Requires-Dist: toml
Requires-Dist: pydantic
Provides-Extra: web
Requires-Dist: dash ; extra == 'web'
